notion_export_enhancer/__init__.py
notion_export_enhancer/__main__.py
notion_export_enhancer/enhancer.py
notion_export_enhancer-0.0.7.dist-info/LICENSE.txt
notion_export_enhancer-0.0.7.dist-info/METADATA
notion_export_enhancer-0.0.7.dist-info/WHEEL
notion_export_enhancer-0.0.7.dist-info/top_level.txt
notion_export_enhancer-0.0.7.dist-info/RECORD
