Metadata-Version: 2.1
Name: notion-export-enhancer
Version: 0.0.7
Summary: Export and _enhance_, takes Notion's export and makes it just a bit more usable.
Home-page: https://github.com/Cobertos/notion_export_enhancer/
Author: Cobertos
Author-email: me+python@cobertos.com
License: MIT
Keywords: notion notion.so notion-py markdown md export enhance enhancer
Platform: UNKNOWN
Classifier: Development Status :: 4 - Beta
Classifier: Intended Audience :: Developers
Classifier: License :: OSI Approved :: MIT License
Classifier: Programming Language :: Python :: 3.6
Classifier: Programming Language :: Python :: 3.7
Classifier: Programming Language :: Python :: 3.8
Classifier: Topic :: Office/Business :: News/Diary
Classifier: Topic :: System :: Filesystems
Classifier: Topic :: Text Processing :: Markup :: Markdown
Classifier: Topic :: Utilities
License-File: LICENSE.txt
Requires-Dist: backoff (>=1.11.0)
Requires-Dist: emoji-extractor (>=1.0.19)
Requires-Dist: notion-cobertos-fork (>=0.0.29)
